pretty_plz/brain.py
pretty_plz/dotenv.py
pretty_plz/env.py
pretty_plz/exceptions.py
pretty_plz/main.py
pretty_plz/return_codes.py
pretty_plz-0.1.6.dist-info/entry_points.txt
pretty_plz-0.1.6.dist-info/WHEEL
pretty_plz-0.1.6.dist-info/METADATA
pretty_plz-0.1.6.dist-info/RECORD
